setup.py
isom2600/__init__.py
isom2600/data.py
isom2600/regression.py
isom2600.egg-info/PKG-INFO
isom2600.egg-info/SOURCES.txt
isom2600.egg-info/dependency_links.txt
isom2600.egg-info/top_level.txt