Metadata-Version: 2.1
Name: isom2600
Version: 3.1
Summary: Toolbox for ISOM2600 
